{
  "name": "admin.login",
  "nodes": [
    {
      "parameters": {
        "httpMethod": "POST",
        "path": "admin-login",
        "responseMode": "responseNode",
        "options": {}
      },
      "id": "webhook-trigger",
      "name": "Webhook Trigger",
      "type": "n8n-nodes-base.webhook",
      "typeVersion": 2,
      "position": [
        250,
        400
      ],
      "webhookId": "admin-login"
    },
    {
      "parameters": {
        "jsCode": "// Extract username and password from body\nconst input = $input.item.json;\nconst body = input.body || input;\nconst headers = input.headers || {};\n\nconst username = body.username || '';\nconst password = body.password || '';\n\nif (!username || !password) {\n  return {\n    json: {\n      error: 'bad_request',\n      status: 400,\n      message: 'Username and password are required'\n    }\n  };\n}\n\nreturn {\n  json: {\n    username: username.trim(),\n    password: password,\n    ip: headers['x-forwarded-for'] || headers['x-real-ip'] || 'unknown',\n    user_agent: headers['user-agent'] || 'unknown'\n  }\n};"
      },
      "id": "extract-credentials",
      "name": "Extract Credentials",
      "type": "n8n-nodes-base.code",
      "typeVersion": 2,
      "position": [
        450,
        400
      ]
    },
    {
      "parameters": {
        "conditions": {
          "options": {
            "caseSensitive": true,
            "leftValue": "",
            "typeValidation": "strict"
          },
          "conditions": [
            {
              "id": "error-check",
              "leftValue": "={{ $json.error }}",
              "rightValue": "",
              "operator": {
                "type": "string",
                "operation": "notEmpty"
              }
            }
          ],
          "combinator": "and"
        },
        "options": {}
      },
      "id": "check-extract-error",
      "name": "IF Extract Error",
      "type": "n8n-nodes-base.if",
      "typeVersion": 2,
      "position": [
        650,
        400
      ]
    },
    {
      "parameters": {
        "respondWith": "text",
        "responseBody": "={{ JSON.stringify($json) }}",
        "options": {
          "responseCode": "={{ $json.status || 400 }}"
        }
      },
      "id": "response-extract-error",
      "name": "Respond Extract Error",
      "type": "n8n-nodes-base.respondToWebhook",
      "typeVersion": 1.1,
      "position": [
        850,
        300
      ]
    },
    {
      "parameters": {
        "operation": "executeQuery",
        "query": "=SELECT id, username, password_hash, is_active\nFROM admin_users\nWHERE username = '{{ $json.username }}'\n  AND is_active = true\nLIMIT 1;",
        "options": {}
      },
      "id": "get-admin-user",
      "name": "Get Admin User",
      "type": "n8n-nodes-base.postgres",
      "typeVersion": 2.4,
      "position": [
        850,
        500
      ],
      "credentials": {
        "postgres": {
          "id": "supabase_postgres",
          "name": "Supabase PostgreSQL"
        }
      }
    },
    {
      "parameters": {
        "conditions": {
          "options": {
            "caseSensitive": true,
            "leftValue": "",
            "typeValidation": "strict"
          },
          "conditions": [
            {
              "id": "user-found",
              "leftValue": "={{ $json.id }}",
              "rightValue": "",
              "operator": {
                "type": "string",
                "operation": "notEmpty"
              }
            }
          ],
          "combinator": "and"
        },
        "options": {}
      },
      "id": "check-user-found",
      "name": "IF User Found",
      "type": "n8n-nodes-base.if",
      "typeVersion": 2,
      "position": [
        1050,
        500
      ]
    },
    {
      "parameters": {
        "respondWith": "text",
        "responseBody": "={{ JSON.stringify({ error: 'unauthorized', status: 401, message: 'Invalid username or password' }) }}",
        "options": {
          "responseCode": 401
        }
      },
      "id": "response-unauthorized",
      "name": "Respond Unauthorized",
      "type": "n8n-nodes-base.respondToWebhook",
      "typeVersion": 1.1,
      "position": [
        1050,
        400
      ]
    },
    {
      "parameters": {
        "jsCode": "// Simple password verification (for now - can be upgraded to bcrypt later)\n// In production, password_hash should be bcrypt hash\nconst adminUser = $input.item.json;\nconst providedPassword = $('Extract Credentials').item.json.password;\n\n// Simple comparison for now (TODO: implement bcrypt)\n// For production, use: const bcrypt = require('bcrypt'); const isValid = bcrypt.compareSync(providedPassword, adminUser.password_hash);\nconst isValid = providedPassword === adminUser.password_hash || adminUser.password_hash === providedPassword;\n\nif (!isValid) {\n  return {\n    json: {\n      error: 'unauthorized',\n      status: 401,\n      message: 'Invalid username or password'\n    }\n  };\n}\n\nreturn {\n  json: {\n    admin_user_id: adminUser.id,\n    username: adminUser.username\n  }\n};"
      },
      "id": "verify-password",
      "name": "Verify Password",
      "type": "n8n-nodes-base.code",
      "typeVersion": 2,
      "position": [
        1250,
        600
      ]
    },
    {
      "parameters": {
        "conditions": {
          "options": {
            "caseSensitive": true,
            "leftValue": "",
            "typeValidation": "strict"
          },
          "conditions": [
            {
              "id": "password-valid",
              "leftValue": "={{ $json.error }}",
              "rightValue": "",
              "operator": {
                "type": "string",
                "operation": "isEmpty"
              }
            }
          ],
          "combinator": "and"
        },
        "options": {}
      },
      "id": "check-password-valid",
      "name": "IF Password Valid",
      "type": "n8n-nodes-base.if",
      "typeVersion": 2,
      "position": [
        1450,
        600
      ]
    },
    {
      "parameters": {
        "respondWith": "text",
        "responseBody": "={{ JSON.stringify($json) }}",
        "options": {
          "responseCode": "={{ $json.status || 401 }}"
        }
      },
      "id": "response-password-invalid",
      "name": "Respond Password Invalid",
      "type": "n8n-nodes-base.respondToWebhook",
      "typeVersion": 1.1,
      "position": [
        1450,
        500
      ]
    },
    {
      "parameters": {
        "operation": "executeQuery",
        "query": "=INSERT INTO admin_sessions (admin_user_id, expires_at, ip, user_agent)\nVALUES (\n  CAST('{{ $json.admin_user_id }}' AS UUID),\n  NOW() + interval '7 days',\n  '{{ $('Webhook Trigger').item.json.headers['x-real-ip'] || $('Webhook Trigger').item.json.headers['x-forwarded-for'] || 'unknown' }}',\n  '{{ $('Webhook Trigger').item.json.headers['user-agent'] || 'unknown' }}'\n)\nRETURNING id, token, expires_at;",
        "options": {}
      },
      "id": "create-session",
      "name": "Create Session",
      "type": "n8n-nodes-base.postgres",
      "typeVersion": 2.4,
      "position": [
        1650,
        700
      ],
      "credentials": {
        "postgres": {
          "id": "supabase_postgres",
          "name": "Supabase PostgreSQL"
        }
      }
    },
    {
      "parameters": {
        "operation": "executeQuery",
        "query": "=UPDATE admin_users\nSET last_login_at = NOW()\nWHERE id = '{{ $('Verify Password').item.json.admin_user_id }}';",
        "options": {}
      },
      "id": "update-last-login",
      "name": "Update Last Login",
      "type": "n8n-nodes-base.postgres",
      "typeVersion": 2.4,
      "position": [
        1850,
        700
      ],
      "credentials": {
        "postgres": {
          "id": "supabase_postgres",
          "name": "Supabase PostgreSQL"
        }
      }
    },
    {
      "parameters": {
        "operation": "insert",
        "schema": {
          "__rl": true,
          "value": "public",
          "mode": "list",
          "cachedResultName": "public"
        },
        "table": {
          "__rl": true,
          "value": "audit_events",
          "mode": "list",
          "cachedResultName": "audit_events"
        },
        "columns": {
          "mappingMode": "defineBelow",
          "value": {
            "action": "admin.login",
            "resource_type": "admin_session",
            "resource_id": "={{ $('Create Session').item.json.id }}",
            "metadata": "={{ JSON.stringify({ admin_user_id: $('Verify Password').item.json.admin_user_id, username: $('Verify Password').item.json.username }) }}",
            "ip": "={{ $('Extract Credentials').item.json.ip }}",
            "user_agent": "={{ $('Extract Credentials').item.json.user_agent }}"
          },
          "matchingColumns": [],
          "schema": []
        },
        "options": {}
      },
      "id": "log-audit-event",
      "name": "Log Audit Event",
      "type": "n8n-nodes-base.postgres",
      "typeVersion": 2.4,
      "position": [
        2050,
        800
      ],
      "continueOnFail": true,
      "credentials": {
        "postgres": {
          "id": "OPy15M2cOLEss5yi",
          "name": "Postgres account"
        }
      }
    },
    {
      "parameters": {
        "jsCode": "// Manual UUID v4 generator\nfunction generateUUIDv4() {\n  const hex = '0123456789abcdef';\n  let uuid = '';\n  for (let i = 0; i < 36; i++) {\n    if (i === 8 || i === 13 || i === 18 || i === 23) {\n      uuid += '-';\n    } else if (i === 14) {\n      uuid += '4';\n    } else if (i === 19) {\n      uuid += hex[(Math.random() * 4 | 8)];\n    } else {\n      uuid += hex[Math.random() * 16 | 0];\n    }\n  }\n  return uuid;\n}\n\nconst session = $('Create Session').item.json;\nconst username = $('Verify Password').item.json.username;\n\nreturn {\n  json: {\n    success: true,\n    data: {\n      token: session.token.toString(),\n      expires_at: session.expires_at,\n      username: username\n    },\n    traceId: generateUUIDv4()\n  }\n};"
      },
      "id": "build-response",
      "name": "Build Response",
      "type": "n8n-nodes-base.code",
      "typeVersion": 2,
      "position": [
        2250,
        700
      ]
    },
    {
      "parameters": {
        "respondWith": "text",
        "responseBody": "={{ JSON.stringify($json) }}",
        "options": {
          "responseCode": 200
        }
      },
      "id": "response-success",
      "name": "Respond Success",
      "type": "n8n-nodes-base.respondToWebhook",
      "typeVersion": 1.1,
      "position": [
        2450,
        700
      ]
    }
  ],
  "connections": {
    "Webhook Trigger": {
      "main": [
        [
          {
            "node": "Extract Credentials",
            "type": "main",
            "index": 0
          }
        ]
      ]
    },
    "Extract Credentials": {
      "main": [
        [
          {
            "node": "IF Extract Error",
            "type": "main",
            "index": 0
          }
        ]
      ]
    },
    "IF Extract Error": {
      "main": [
        [
          {
            "node": "Respond Extract Error",
            "type": "main",
            "index": 0
          }
        ],
        [
          {
            "node": "Get Admin User",
            "type": "main",
            "index": 0
          }
        ]
      ]
    },
    "Get Admin User": {
      "main": [
        [
          {
            "node": "IF User Found",
            "type": "main",
            "index": 0
          }
        ]
      ]
    },
    "IF User Found": {
      "main": [
        [
          {
            "node": "Respond Unauthorized",
            "type": "main",
            "index": 0
          }
        ],
        [
          {
            "node": "Verify Password",
            "type": "main",
            "index": 0
          }
        ]
      ]
    },
    "Verify Password": {
      "main": [
        [
          {
            "node": "IF Password Valid",
            "type": "main",
            "index": 0
          }
        ]
      ]
    },
    "IF Password Valid": {
      "main": [
        [
          {
            "node": "Respond Password Invalid",
            "type": "main",
            "index": 0
          }
        ],
        [
          {
            "node": "Create Session",
            "type": "main",
            "index": 0
          }
        ]
      ]
    },
    "Create Session": {
      "main": [
        [
          {
            "node": "Update Last Login",
            "type": "main",
            "index": 0
          }
        ]
      ]
    },
    "Update Last Login": {
      "main": [
        [
          {
            "node": "Log Audit Event",
            "type": "main",
            "index": 0
          }
        ]
      ]
    },
    "Log Audit Event": {
      "main": [
        [
          {
            "node": "Build Response",
            "type": "main",
            "index": 0
          }
        ]
      ]
    },
    "Build Response": {
      "main": [
        [
          {
            "node": "Respond Success",
            "type": "main",
            "index": 0
          }
        ]
      ]
    }
  },
  "settings": {
    "executionOrder": "v1"
  },
  "staticData": null,
  "tags": [],
  "triggerCount": 0,
  "updatedAt": "2025-11-06T00:00:00.000Z",
  "versionId": "1"
}